fastapi_tools/config/__init__.py
fastapi_tools/config/py.typed
fastapi_tools_config-0.1.4.dist-info/METADATA
fastapi_tools_config-0.1.4.dist-info/WHEEL
fastapi_tools_config-0.1.4.dist-info/RECORD
